sep.cpython-39-darwin.so
sdss_sep-1.2.7.dist-info/RECORD
sdss_sep-1.2.7.dist-info/WHEEL
sdss_sep-1.2.7.dist-info/top_level.txt
sdss_sep-1.2.7.dist-info/METADATA
sdss_sep-1.2.7.dist-info/licenses/AUTHORS.md
